nvidia/dali/_utils/eager_utils.py
nvidia/dali/plugin_manager.py
nvidia/dali/_utils/__init__.py
nvidia/dali/_utils/external_source_impl.py
nvidia/dali/_utils/dali_trace.py
nvidia/dali/_debug_mode.py
nvidia/dali/_utils/hacks.py
nvidia/dali/_autograph/impl/__init__.py
nvidia/dali/_utils/autoserialize.py
nvidia/dali/_autograph/utils/__init__.py
nvidia/dali/_autograph/utils/ag_logging.py
nvidia/dali/_autograph/utils/all_utils.py
nvidia/dali/external_source.pyi
nvidia/dali/_autograph/operators/variables.py
nvidia/dali/_autograph/converters/conditional_expressions.py
nvidia/dali/_autograph/converters/lists.py
nvidia/dali/_autograph/pyct/common_transformers/anf.py
nvidia/dali/_autograph/converters/logical_expressions.py
nvidia/dali/backend.pyi
nvidia/dali/tfrecord.pyi
nvidia/dali/_autograph/operators/data_structures.py
nvidia/dali/include/boost/preprocessor/array/data.hpp
nvidia/dali/include/dali/operators/reader/loader/lmdb.h
nvidia/dali/include/dali/pipeline/operator/arg_helper.h
nvidia/dali/include/dali/operators/video/legacy/reader/video_reader_op.h
nvidia/dali/include/dali/kernels/slice/slice_cpu.h
nvidia/dali/include/dali/core/geom/box.h
nvidia/dali/include/dali/pipeline/util/bounding_box_utils.h
nvidia/dali/include/dali/util/cufile.h
nvidia/dali/include/dali/kernels/common/join/tensor_join_gpu.h
nvidia/dali/include/boost/preprocessor/arithmetic/add.hpp
nvidia/dali/include/dali/kernels/reduce/reduce_axes_gpu_impl.cuh
nvidia/dali/include/boost/preprocessor/list/detail/fold_right.hpp
nvidia/dali/include/dali/operators/reader/fits_reader_gpu_op.h
nvidia/dali/include/boost/preprocessor/iteration/detail/iter/limits/reverse5_512.hpp
nvidia/dali/include/dali/operators/generic/reduce/mean.h
nvidia/dali/include/boost/preprocessor/punctuation/comma.hpp
nvidia/dali/include/dali/operators/decoder/audio/audio_decoder_impl.h
nvidia/dali/experimental/dynamic/experimental/readers/__init__.pyi
nvidia/dali/include/boost/preprocessor/variadic/limits/elem_64.hpp
nvidia_dali_cuda120-1.53.0.dist-info/entry_points.txt
nvidia_dali_cuda120-1.53.0.dist-info/METADATA
nvidia_dali_cuda120-1.53.0.dist-info/top_level.txt
nvidia_dali_cuda120-1.53.0.dist-info/WHEEL
nvidia_dali_cuda120-1.53.0.dist-info/RECORD
